podaac/forge_tig_config_generator/__init__.py
podaac/forge_tig_config_generator/generate_config.py
podaac/forge_tig_config_generator/schema.json
forge_tig_config_generator-0.2.0.dist-info/LICENSE
forge_tig_config_generator-0.2.0.dist-info/METADATA
forge_tig_config_generator-0.2.0.dist-info/WHEEL
forge_tig_config_generator-0.2.0.dist-info/entry_points.txt
forge_tig_config_generator-0.2.0.dist-info/RECORD
