Metadata-Version: 2.3
Name: forge-tig-config-generator
Version: 0.2.0
Summary: Tool to generate podaac forge and tig configurations
Author: Simon Liu
Author-email: simon.liu@jpl.nasa.gov
Requires-Python: >=3.10,<4.0
Classifier: Programming Language :: Python :: 3
Classifier: Programming Language :: Python :: 3.10
Classifier: Programming Language :: Python :: 3.11
Classifier: Programming Language :: Python :: 3.12
Classifier: Programming Language :: Python :: 3.13
Requires-Dist: click (>=8.1,<9.0)
Requires-Dist: jsonschema (>=4.23.0,<5.0.0)
Requires-Dist: openpyxl (>=3.1.5,<4.0.0)
Requires-Dist: pandas (>=2.2.3,<3.0.0)
